vsrc/top.v
`timescale 1ns/1ns

module top(
  input  wire clk,
  input  wire rst_n,
  input  wire a,
  input  wire b,
  output wire f,
  output reg [7:0] data,

  output reg [7:0] led
);
  assign f = a ^ b;
  
  always@(posedge clk or negedge rst_n) begin
    if(rst_n == 1'b0)
      data[7:0] <= 8'h00;
    else
      data[7:0] <= data[7:0] + 1'b1;
  end


  reg [15:0] count;
  always@(posedge clk or negedge rst_n) begin
    if(rst_n == 1'b0) begin
      led[7:0] <= 8'b1000_0000;
      count <= 'd0;
    end
    else begin
      if(count == 16'hff_ff) led[7:0] <= {led[6:0],led[7]};
      count <= (count == 16'hff_ff) ? 'd0 : count + 1'b1;
    end
  end


  initial begin
      $display("\nHello World! --cyril\n");
      $finish;
  end

endmodule

waveform.vcd
$version Generated by VerilatedVcd $end
$date Fri Oct  7 10:54:07 2022 $end
$timescale 1ns $end

 $scope module TOP $end
  $var wire  1 % a $end
  $var wire  1 & b $end
  $var wire  1 # clk $end
  $var wire  8 ( data [7:0] $end
  $var wire  1 ' f $end
  $var wire  8 ) led [7:0] $end
  $var wire  1 $ rst_n $end
  $scope module top $end
   $var wire  1 % a $end
   $var wire  1 & b $end
   $var wire  1 # clk $end
   $var wire 16 * count [15:0] $end
   $var wire  8 ( data [7:0] $end
   $var wire  1 ' f $end
   $var wire  8 ) led [7:0] $end
   $var wire  1 $ rst_n $end
  $upscope $end
 $upscope $end
$enddefinitions $end


#8
0#
0$
1%
0&
1'
b00000000 (
b00000000 )
b0000000000000000 *
#10
1#
b10000000 )
#15
0#
#18
1&
0'
#20
1#
#25
0#
#28
#30
1#
#35
0#
#38
0%
0&
#40
1#
#45
0#
#48
1%
1&
#50
1#
#55
0#
#58
0%
1'
#60
1#
#65
0#
#68
#70
1#
#75
0#
#78
1%
0&
#80
1#
#85
0#
#88
0%
0'
#90
1#
#95
0#
#98
#100
1#
#105
0#
#108
1%
1'
#110
1#
#115
0#
#118
1&
0'
#120
1#
#125
0#
#128
0%
0&
#130
1#
#135
0#
#138
1&
1'
#140
1#
#145
0#
#148
1%
0'
#150
1#
#155
0#
#158
0&
1'
#160
1#
#165
0#
#168
0%
0'
#170
1#
#175
0#
#178
1%
1&
#180
1#
#185
0#
#188
0&
1'
#190
1#
#195
0#
#198
#200
1#
#205
0#
#208
1&
0'
#210
1#
#215
0#
#218
#220
1#
#225
0#
#228
0%
1'
#230
1#
#235
0#
#238
0&
0'
#240
1#
#245
0#
#248
1%
1'
#250
1#
#255
0#
#258
#260
1#
#265
0#
#268
#270
1#
#275
0#
#278
0%
1&
#280
1#
#285
0#
#288
0&
0'
#290
1#
#295
0#
#298
1&
1'
#300
1#
#305
0#
#308
1%
0'
#310
1#
#315
0#
#318
0%
1'
#320
1#
#325
0#
#328
#330
1#
#335
0#
#338
#340
1#
#345
0#
#348
1%
0'
#350
1#
#355
0#
#358
0%
1'
#360
1#
#365
0#
#368
#370
1#
#375
0#
#378
#380
1#
#385
0#
#388
0&
0'
#390
1#
#395
0#
#398
1%
1'
#400
1#
#405
0#
#408
#410
1#
#415
0#
#418
0%
0'
#420
1#
#425
0#
#428
#430
1#
#435
0#
#438
1%
1&
#440
1#
#445
0#
#448
0%
1'
#450
1#
#455
0#
#458
0&
0'
#460
1#
#465
0#
#468
#470
1#
#475
0#
#478
1%
1'
#480
1#
#485
0#
#488
0%
0'
#490
1#
#495
0#
#498
1&
1'
#500
1#
#505
0#
#508
1%
0&
#510
1#
#515
0#
#518
0%
0'
#520
1#
#525
0#
#528
1%
1&
#530
1#
#535
0#
#538
0&
1'
#540
1#
#545
0#
#548
#550
1#
#555
0#
#558
0%
0'
#560
1#
#565
0#
#568
1%
1'
#570
1#
#575
0#
#578
0%
1&
#580
1#
#585
0#
#588
1%
0'
#590
1#
#595
0#
#598
0%
1'
#600
1#
#605
0#
#608
#610
1#
#615
0#
#618
1%
0'
#620
1#
#625
0#
#628
#630
1#
#635
0#
#638
#640
1#
#645
0#
#648
#650
1#
#655
0#
#658
0&
1'
#660
1#
#665
0#
#668
1&
0'
#670
1#
#675
0#
#678
0%
1'
#680
1#
#685
0#
#688
#690
1#
#695
0#
#698
1%
0&
#700
1#
#705
0#
#708
0%
1&
#710
1#
#715
0#
#718
#720
1#
#725
0#
#728
1%
0'
#730
1#
#735
0#
#738
0%
0&
#740
1#
#745
0#
#748
1&
1'
#750
1#
#755
0#
#758
#760
1#
#765
0#
#768
#770
1#
#775
0#
#778
#780
1#
#785
0#
#788
#790
1#
#795
0#
#798
1%
0'
#800
1#
#805
0#
#808
0&
1'
#810
1#
#815
0#
#818
0%
0'
#820
1#
#825
0#
#828
1%
1'
#830
1#
#835
0#
#838
#840
1#
#845
0#
#848
0%
0'
#850
1#
#855
0#
#858
#860
1#
#865
0#
#868
1%
1'
#870
1#
#875
0#
#878
1&
0'
#880
1#
#885
0#
#888
#890
1#
#895
0#
#898
0&
1'
#900
1#
#905
0#
#908
0%
1&
#910
1#
#915
0#
#918
1%
0&
#920
1#
#925
0#
#928
1&
0'
#930
1#
#935
0#
#938
0%
1'
#940
1#
#945
0#
#948
#950
1#
#955
0#
#958
1%
0'
#960
1#
#965
0#
#968
#970
1#
#975
0#
#978
0%
0&
#980
1#
#985
0#
#988
1%
1&
#990
1#
#995
0#
#998
0%
1'
#1000
1#
#1005
0#
#1008
0&
0'
#1010
1#
#1015
0#
#1018
1%
1&
#1020
1#
#1025
0#
#1028
0&
1'
#1030
1#
#1035
0#
#1038
0%
0'
#1040
1#
#1045
0#
#1048
#1050
1#
#1055
0#
#1058
#1060
1#
#1065
0#
#1068
1%
1&
#1070
1#
#1075
0#
#1078
0&
1'
#1080
1#
#1085
0#
#1088
0%
1&
#1090
1#
#1095
0#
#1098
#1100
1#
#1105
0#
#1108
#1110
1#
#1115
0#
#1118
#1120
1#
#1125
0#
#1128
0&
0'
#1130
1#
#1135
0#
#1138
1%
1&
#1140
1#
#1145
0#
#1148
0%
0&
#1150
1#
#1155
0#
#1158
1%
1'
#1160
1#
#1165
0#
#1168
0%
0'
#1170
1#
#1175
0#
#1178
1%
1&
#1180
1#
#1185
0#
#1188
0&
1'
#1190
1#
#1195
0#
#1198
0%
1&
#1200
1#
#1205
0#
#1208
0&
0'
#1210
1#
#1215
0#
#1218
1%
1&
#1220
1#
#1225
0#
#1228
0%
0&
#1230
1#
#1235
0#
#1238
#1240
1#
#1245
0#
#1248
1%
1'
#1250
1#
#1255
0#
#1258
1&
0'
#1260
1#
#1265
0#
#1268
0&
1'
#1270
1#
#1275
0#
#1278
0%
1&
#1280
1#
#1285
0#
#1288
0&
0'
#1290
1#
#1295
0#
#1298
#1300
1#
#1305
0#
#1308
1&
1'
#1310
1#
#1315
0#
#1318
0&
0'
#1320
1#
#1325
0#
#1328
#1330
1#
#1335
0#
#1338
1&
1'
#1340
1#
#1345
0#
#1348
0&
0'
#1350
1#
#1355
0#
#1358
#1360
1#
#1365
0#
#1368
1&
1'
#1370
1#
#1375
0#
#1378
1%
0&
#1380
1#
#1385
0#
#1388
0%
1&
#1390
1#
#1395
0#
#1398
1%
0'
#1400
1#
#1405
0#
#1408
0&
1'
#1410
1#
#1415
0#
#1418
#1420
1#
#1425
0#
#1428
0%
1&
#1430
1#
#1435
0#
#1438
1%
0'
#1440
1#
#1445
0#
#1448
0&
1'
#1450
1#
#1455
0#
#1458
1&
0'
#1460
1#
#1465
0#
#1468
0&
1'
#1470
1#
#1475
0#
#1478
0%
1&
#1480
1#
#1485
0#
#1488
0&
0'
#1490
1#
#1495
0#
#1498
#1500
1#
#1505
0#
#1508
#1510
1#
#1515
0#
#1518
#1520
1#
#1525
0#
#1528
1&
1'
#1530
1#
#1535
0#
#1538
1%
0&
#1540
1#
#1545
0#
#1548
#1550
1#
#1555
0#
#1558
#1560
1#
#1565
0#
#1568
0%
0'
#1570
1#
#1575
0#
#1578
1%
1&
#1580
1#
#1585
0#
#1588
0%
0&
#1590
1#
#1595
0#
#1598
1&
1'
#1600
1#
#1605
0#
#1608
#1610
1#
#1615
0#
#1618
1%
0&
#1620
1#
#1625
0#
#1628
1&
0'
#1630
1#
#1635
0#
#1638
#1640
1#
#1645
0#
#1648
0&
1'
#1650
1#
#1655
0#
#1658
1&
0'
#1660
1#
#1665
0#
#1668
0%
1'
#1670
1#
#1675
0#
#1678
1%
0&
#1680
1#
#1685
0#
#1688
#1690
1#
#1695
0#
#1698
0%
0'
#1700
1#
#1705
0#
#1708
#1710
1#
#1715
0#
#1718
1&
1'
#1720
1#
#1725
0#
#1728
#1730
1#
#1735
0#
#1738
0&
0'
#1740
1#
#1745
0#
#1748
#1750
1#
#1755
0#
#1758
#1760
1#
#1765
0#
#1768
1%
1&
#1770
1#
#1775
0#
#1778
0%
1'
#1780
1#
#1785
0#
#1788
0&
0'
#1790
1#
#1795
0#
#1798
1&
1'
#1800
1#
#1805
0#
#1808
0&
0'
#1810
1#
#1815
0#
#1818
#1820
1#
#1825
0#
#1828
1%
1&
#1830
1#
#1835
0#
#1838
0&
1'
#1840
1#
#1845
0#
#1848
0%
1&
#1850
1#
#1855
0#
#1858
0&
0'
#1860
1#
#1865
0#
#1868
1%
1&
#1870
1#
#1875
0#
#1878
0&
1'
#1880
1#
#1885
0#
#1888
0%
1&
#1890
1#
#1895
0#
#1898
0&
0'
#1900
1#
#1905
0#
#1908
1%
1'
#1910
1#
#1915
0#
#1918
1&
0'
#1920
1#
#1925
0#
#1928
#1930
1#
#1935
0#
#1938
0%
1'
#1940
1#
#1945
0#
#1948
1%
0&
#1950
1#
#1955
0#
#1958
0%
1&
#1960
1#
#1965
0#
#1968
0&
0'
#1970
1#
#1975
0#
#1978
#1980
1#
#1985
0#
#1988
1&
1'
#1990
1#
#1995
0#
#1998
0&
0'
